bilbyai/__init__.py
bilbyai/source_label_map/__init__.py
bilbyai/source_label_map/source_label_map.py
bilbyai_source_label_map-0.2.8.dist-info/METADATA
bilbyai_source_label_map-0.2.8.dist-info/WHEEL
bilbyai_source_label_map-0.2.8.dist-info/RECORD
