Metadata-Version: 2.1
Name: bilbyai-source-label-map
Version: 0.2.8
Summary: Converts news sources into human-friendly labels
Author: David Lee
Author-email: leetdavidu@gmail.com
Requires-Python: >=3.9
Classifier: Programming Language :: Python :: 3
Classifier: Programming Language :: Python :: 3.9
Classifier: Programming Language :: Python :: 3.10
Classifier: Programming Language :: Python :: 3.11
Classifier: Programming Language :: Python :: 3.12
